rulerunner_sdk/__init__.py
rulerunner_sdk/client.py
rulerunner_sdk-0.3.0.dist-info/METADATA
rulerunner_sdk-0.3.0.dist-info/WHEEL
rulerunner_sdk-0.3.0.dist-info/top_level.txt
rulerunner_sdk-0.3.0.dist-info/RECORD
